esiosapy/__init__.py
esiosapy/client.py
esiosapy/managers/archive_manager.py
esiosapy/managers/indicator_manager.py
esiosapy/managers/offer_indicator_manager.py
esiosapy/models/archive/archive.py
esiosapy/models/archive/archive_date_type.py
esiosapy/models/archive/archive_download.py
esiosapy/models/archive/taxonomy_term.py
esiosapy/models/archive/vocabulary.py
esiosapy/models/indicator/geo_agg.py
esiosapy/models/indicator/geo_trunc.py
esiosapy/models/indicator/indicator.py
esiosapy/models/indicator/time_agg.py
esiosapy/models/indicator/time_trunc.py
esiosapy/models/offer_indicator/offer_indicator.py
esiosapy/utils/request_helper.py
esiosapy/utils/zip_utils.py
esiosapy-1.0.4.dist-info/LICENSE
esiosapy-1.0.4.dist-info/METADATA
esiosapy-1.0.4.dist-info/WHEEL
esiosapy-1.0.4.dist-info/RECORD
