Metadata-Version: 2.1
Name: esiosapy
Version: 1.0.4
Summary: Unofficial ESIOS API Python library. Up to date and fully equipped.
License: GPL-3.0 License 
Author: M4RC0Sx
Requires-Python: >=3.8,<4.0
Classifier: License :: Other/Proprietary License
Classifier: Programming Language :: Python :: 3
Classifier: Programming Language :: Python :: 3.8
Classifier: Programming Language :: Python :: 3.9
Classifier: Programming Language :: Python :: 3.10
Classifier: Programming Language :: Python :: 3.11
Classifier: Programming Language :: Python :: 3.12
Requires-Dist: pydantic (>=2.5.3,<3.0.0)
Requires-Dist: requests (>=2.31.0,<3.0.0)
